setup.py
tests/__init__.py
tests/demo1.py
tests/demo2.py
thanos_fsm/__init__.py
thanos_fsm/base.py
thanos_fsm.egg-info/PKG-INFO
thanos_fsm.egg-info/SOURCES.txt
thanos_fsm.egg-info/dependency_links.txt
thanos_fsm.egg-info/top_level.txt